siggi/__init__.py
siggi/calcIG.py
siggi/filters.py
siggi/mathUtils.py
siggi/plotting.py
siggi/siggi.py
siggi/siggiBase.py
siggi/spectra.py
siggi/data/Inst.10E10.1Z.spec.gz
siggi/data/Inst.64E08.1Z.spec.gz
siggi/data/lsst_baseline_throughputs/LSSTfilters.png
siggi/data/lsst_baseline_throughputs/README.md
siggi/data/lsst_baseline_throughputs/atmos_10.dat
siggi/data/lsst_baseline_throughputs/atmos_std.dat
siggi/data/lsst_baseline_throughputs/darksky.dat
siggi/data/lsst_baseline_throughputs/detector.dat
siggi/data/lsst_baseline_throughputs/filter_g.dat
siggi/data/lsst_baseline_throughputs/filter_i.dat
siggi/data/lsst_baseline_throughputs/filter_r.dat
siggi/data/lsst_baseline_throughputs/filter_u.dat
siggi/data/lsst_baseline_throughputs/filter_y.dat
siggi/data/lsst_baseline_throughputs/filter_z.dat
siggi/data/lsst_baseline_throughputs/hardware_g.dat
siggi/data/lsst_baseline_throughputs/hardware_i.dat
siggi/data/lsst_baseline_throughputs/hardware_r.dat
siggi/data/lsst_baseline_throughputs/hardware_u.dat
siggi/data/lsst_baseline_throughputs/hardware_y.dat
siggi/data/lsst_baseline_throughputs/hardware_z.dat
siggi/data/lsst_baseline_throughputs/lens1.dat
siggi/data/lsst_baseline_throughputs/lens2.dat
siggi/data/lsst_baseline_throughputs/lens3.dat
siggi/data/lsst_baseline_throughputs/m1.dat
siggi/data/lsst_baseline_throughputs/m2.dat
siggi/data/lsst_baseline_throughputs/m3.dat
siggi/data/lsst_baseline_throughputs/total_g.dat
siggi/data/lsst_baseline_throughputs/total_i.dat
siggi/data/lsst_baseline_throughputs/total_r.dat
siggi/data/lsst_baseline_throughputs/total_u.dat
siggi/data/lsst_baseline_throughputs/total_y.dat
siggi/data/lsst_baseline_throughputs/total_z.dat
siggi/lsst_utils/Bandpass.py
siggi/lsst_utils/BandpassDict.py
siggi/lsst_utils/LSSTdefaults.py
siggi/lsst_utils/PhotometricParameters.py
siggi/lsst_utils/PhysicalParameters.py
siggi/lsst_utils/README.md
siggi/lsst_utils/Sed.py
siggi/lsst_utils/SignalToNoise.py
siggi-0.1.5.dist-info/METADATA
siggi-0.1.5.dist-info/RECORD
siggi-0.1.5.dist-info/WHEEL
siggi-0.1.5.dist-info/top_level.txt
