Metadata-Version: 2.1
Name: siggi
Version: 0.1.5
Summary: Spectral Information Gain Optimization
Home-page: https://github.com/jbkalmbach/siggi
Author: Bryce Kalmbach
Author-email: brycek@uw.edu
License: UNKNOWN
Platform: UNKNOWN
Classifier: Development Status :: 3 - Alpha
Classifier: License :: OSI Approved :: GNU General Public License v3 (GPLv3)
Classifier: Intended Audience :: Science/Research
Classifier: Operating System :: OS Independent
Classifier: Programming Language :: Python
